gverify/__init__.py
gverify/exceptions.py
gverify/oauth.py
gverify/scopes.py
gverify-0.2.2.dist-info/LICENSE
gverify-0.2.2.dist-info/METADATA
gverify-0.2.2.dist-info/WHEEL
gverify-0.2.2.dist-info/top_level.txt
gverify-0.2.2.dist-info/RECORD
