Metadata-Version: 2.2
Name: gverify
Version: 0.2.2
Summary: A python library for authenticating requests for various google services including ``gmail``, ``youtube``, ``drive`` and ``calendar``.
Home-page: https://youtube-wrapper.readthedocs.io/en/latest/index.html
Author: Lyle Okoth
Author-email: lyleokoth-mlengineer@gmail.com
License: MIT
Keywords: google-auth,google authentication,google oauth,google oauth2,google api,google api client,google api python client,google api python,google api client python,google api python client,google api python,google api client python,google api python client,google api python
Classifier: Intended Audience :: Developers
Classifier: License :: OSI Approved :: MIT License
Classifier: Programming Language :: Python
Classifier: Programming Language :: Python :: 3
Classifier: Programming Language :: Python :: 3.10
Classifier: Programming Language :: Python :: 3.11
Classifier: Programming Language :: Python :: 3.12
Classifier: Operating System :: OS Independent
License-File: LICENSE
Requires-Dist: google-api-python-client
Requires-Dist: google-auth-oauthlib
Requires-Dist: pydantic
Requires-Dist: pydantic-settings
Dynamic: author
Dynamic: author-email
Dynamic: classifier
Dynamic: description
Dynamic: description-content-type
Dynamic: home-page
Dynamic: keywords
Dynamic: license
Dynamic: requires-dist
Dynamic: summary
